test/WeixinOpenClientTest.py
test/__init__.py
weixin_open_api/__init__.py
weixin_open_api/logger.py
weixin_open_api/version.py
weixin_open_api/weixin_open_api.py
weixin_open_api/weixin_open_client.py
weixin_open_api/utils/__init__.py
weixin_open_api/utils/sign.py
weixin_open_api-0.0.5.dist-info/METADATA
weixin_open_api-0.0.5.dist-info/WHEEL
weixin_open_api-0.0.5.dist-info/top_level.txt
weixin_open_api-0.0.5.dist-info/zip-safe
weixin_open_api-0.0.5.dist-info/RECORD
