Metadata-Version: 2.1
Name: weixin-open-api
Version: 0.0.5
Summary: 微信开放接口封装库
Home-page: https://github.com/mouday/weixin-open-api
Author: Peng Shiyu
Author-email: pengshiyuyx@gmail.com
License: MIT
Keywords: w,e,i,x,i,n, ,a,p,i
Platform: UNKNOWN
Classifier: Programming Language :: Python :: 2.7
Classifier: Programming Language :: Python :: 3
Requires-Dist: six
Requires-Dist: session-request
Requires-Dist: mo-cache
